odoo/addons/contract_queue_job/README.rst
odoo/addons/contract_queue_job/__init__.py
odoo/addons/contract_queue_job/__manifest__.py
odoo/addons/contract_queue_job/data/ir_config_parameter.xml
odoo/addons/contract_queue_job/data/queue_job_channel.xml
odoo/addons/contract_queue_job/data/queue_job_function.xml
odoo/addons/contract_queue_job/i18n/contract_queue_job.pot
odoo/addons/contract_queue_job/i18n/es.po
odoo/addons/contract_queue_job/i18n/fr.po
odoo/addons/contract_queue_job/i18n/it.po
odoo/addons/contract_queue_job/i18n/nl.po
odoo/addons/contract_queue_job/models/__init__.py
odoo/addons/contract_queue_job/models/contract_contract.py
odoo/addons/contract_queue_job/models/contract_line.py
odoo/addons/contract_queue_job/readme/CONTRIBUTORS.md
odoo/addons/contract_queue_job/readme/DESCRIPTION.md
odoo/addons/contract_queue_job/readme/USAGE.md
odoo/addons/contract_queue_job/static/description/icon.png
odoo/addons/contract_queue_job/static/description/index.html
odoo/addons/contract_queue_job/tests/__init__.py
odoo/addons/contract_queue_job/tests/test_contract_line_queue_job.py
odoo/addons/contract_queue_job/tests/test_contract_queue_job.py
odoo/addons/contract_queue_job/wizards/__init__.py
odoo/addons/contract_queue_job/wizards/contract_manually_create_invoice.py
odoo/addons/contract_queue_job/wizards/contract_manually_create_invoice.xml
odoo_addon_contract_queue_job-18.0.1.0.0.6.dist-info/METADATA
odoo_addon_contract_queue_job-18.0.1.0.0.6.dist-info/WHEEL
odoo_addon_contract_queue_job-18.0.1.0.0.6.dist-info/top_level.txt
odoo_addon_contract_queue_job-18.0.1.0.0.6.dist-info/RECORD
